m360/__init__.py
m360/awareness.py
m360/constants.py
m360/maintenance.py
m360/rbac.py
m360/registry.py
m360/sdk.py
m360/service.py
m360/tenant.py
m360/ttlcache.py
m360/user.py
m360/utils.py
m360/validator.py
m360/frameworks/__init__.py
m360/frameworks/helper.py
m360/frameworks/django/__init__.py
m360/frameworks/django/middleware.py
m360/frameworks/django/settings.py
m360/frameworks/flask/__init__.py
m360/frameworks/flask/middleware.py
m360/frameworks/flask/settings.py
m360/gateway/__init__.py
m360/gateway/connector.py
m360/schemas/__init__.py
m360/schemas/api.json
m360/schemas/contract.json
m360/schemas/middleware.json
test/__init__.py
test/assets/__init__.py
test/assets/contract.json
test/unit/__init__.py
test/unit/helper.py
test/unit/test_awareness.py
test/unit/test_connector.py
test/unit/test_django_middleware.py
test/unit/test_flask_middleware.py
test/unit/test_maintenance.py
test/unit/test_rbac.py
test/unit/test_registry.py
test/unit/test_service.py
test/unit/test_tenant.py
test/unit/test_user.py
test/unit/test_util.py
m360_middleware-0.0.8.dist-info/LICENSE
m360_middleware-0.0.8.dist-info/METADATA
m360_middleware-0.0.8.dist-info/WHEEL
m360_middleware-0.0.8.dist-info/top_level.txt
m360_middleware-0.0.8.dist-info/RECORD
