Metadata-Version: 2.1
Name: m360-middleware
Version: 0.0.8
Summary: M360 middleware library for Python Django and Flask
Home-page: https://www.corsairm360.com/
Author: Hazkiel Gabriel
Author-email: hazkiel@corsairm360.com
License: apache-2.0
Keywords: M360,M360API,Middleware,Django,Flask
Requires-Python: >=3.6
License-File: LICENSE
Requires-Dist: docker
Requires-Dist: jsonschema
Requires-Dist: requests
Requires-Dist: Werkzeug
